{"frames": [

{
	"filename": "front",
	"frame": {"x":1,"y":1,"w":391,"h":1022},
	"rotated": false,
	"trimmed": false,
	"spriteSourceSize": {"x":0,"y":0,"w":391,"h":1022},
	"sourceSize": {"w":391,"h":1022}
},
{
	"filename": "side",
	"frame": {"x":394,"y":1,"w":40,"h":1022},
	"rotated": false,
	"trimmed": false,
	"spriteSourceSize": {"x":0,"y":0,"w":40,"h":1022},
	"sourceSize": {"w":40,"h":1022}
}],
"meta": {
	"app": "https://www.codeandweb.com/texturepacker",
	"version": "1.0",
	"image": "sheet.png",
	"format": "RGBA8888",
	"size": {"w":512,"h":1024},
	"scale": "1",
	"smartupdate": "$TexturePacker:SmartUpdate:6be9cd388680e4c951c16f551bcf30e5:96a4913d9c9676790b25cc5375f35164:9c44ecd7e9a522007eaff2949095bc1d$"
}
}
